houdiniutils/__init__.py
houdiniutils/post_install.py
houdiniutils/textureTools/__init__.py
houdiniutils/textureTools/main.py
houdiniutils/textureTools/renameTexture.py
houdiniutils/textureTools/tex_id_manager.py
houdiniutils/textureTools/textureID.json
houdiniutils-0.1.6.dist-info/LICENSE
houdiniutils-0.1.6.dist-info/METADATA
houdiniutils-0.1.6.dist-info/WHEEL
houdiniutils-0.1.6.dist-info/entry_points.txt
houdiniutils-0.1.6.dist-info/RECORD
