Metadata-Version: 2.1
Name: houdiniutils
Version: 0.1.6
Summary: All related tools and utilities
License: MIT
Author: Suhail
Author-email: suhailece@gmail.com
Requires-Python: >=3.10.10,<4.0.0
Classifier: License :: OSI Approved :: MIT License
Classifier: Programming Language :: Python :: 3
Classifier: Programming Language :: Python :: 3.11
Classifier: Programming Language :: Python :: 3.12
